upit/__init__.py
upit/_modidx.py
upit/_nbdev.py
upit/metrics.py
upit/data/__init__.py
upit/data/unpaired.py
upit/inference/__init__.py
upit/inference/cyclegan.py
upit/models/__init__.py
upit/models/cyclegan.py
upit/models/dualgan.py
upit/models/ganilla.py
upit/models/junyanz.py
upit/tracking/__init__.py
upit/tracking/wandb.py
upit/train/__init__.py
upit/train/cyclegan.py
upit/train/dualgan.py
upit-0.2.2.dist-info/LICENSE
upit-0.2.2.dist-info/METADATA
upit-0.2.2.dist-info/WHEEL
upit-0.2.2.dist-info/entry_points.txt
upit-0.2.2.dist-info/top_level.txt
upit-0.2.2.dist-info/RECORD
