Metadata-Version: 2.1
Name: upit
Version: 0.2.2
Summary: Unpaired Image-to-Image Translation with PyTorch+fastai
Home-page: https://github.com/tmabraham/UPIT/tree/master/
Author: Tanishq Abraham
Author-email: tmabraham@ucdavis.edu
License: Apache Software License 2.0
Keywords: None
Platform: UNKNOWN
Classifier: Development Status :: 3 - Alpha
Classifier: Intended Audience :: Developers
Classifier: Natural Language :: English
Classifier: Programming Language :: Python :: 3.6
Classifier: Programming Language :: Python :: 3.7
Classifier: Programming Language :: Python :: 3.8
Classifier: Programming Language :: Python :: 3.9
Classifier: Programming Language :: Python :: 3.10
Classifier: License :: OSI Approved :: Apache Software License
Requires-Python: >=3.6
License-File: LICENSE
Requires-Dist: fastai (>=2.3.0)
Requires-Dist: fastcore (>=1.3.19)
Requires-Dist: torchvision (>=0.8)
Requires-Dist: matplotlib
Requires-Dist: pandas
Requires-Dist: requests
Requires-Dist: pyyaml
Requires-Dist: fastprogress (>=0.2.4)
Requires-Dist: pillow
Requires-Dist: scikit-learn
Requires-Dist: scipy
Requires-Dist: spacy
Requires-Dist: datasets
Requires-Dist: huggingface-hub
Provides-Extra: dev
Requires-Dist: nbdev (>=1.1.13) ; extra == 'dev'
Requires-Dist: gradio ; extra == 'dev'
Requires-Dist: wandb ; extra == 'dev'
Requires-Dist: albumentations ; extra == 'dev'
